notices/__init__.py
notices/admin.py
notices/apps.py
notices/context_processors.py
notices/example_project/__init__.py
notices/example_project/example_app/__init__.py
notices/example_project/example_app/migrations/__init__.py
notices/example_project/example_app/templates/example_app/home.html
notices/example_project/example_app/views.py
notices/example_project/example_project/__init__.py
notices/example_project/example_project/asgi.py
notices/example_project/example_project/settings.py
notices/example_project/example_project/urls.py
notices/example_project/example_project/wsgi.py
notices/example_project/manage.py
notices/migrations/0001_initial.py
notices/migrations/0002_alter_notice_version.py
notices/migrations/0003_notice_timeout_seconds.py
notices/migrations/0004_notice_starts_at.py
notices/migrations/__init__.py
notices/models.py
notices/static/notices/css/notices.css
notices/static/notices/js/notices.js
notices/templates/notices/notices.html
notices/templates/notices/notices_clear.html
notices/templatetags/__init__.py
notices/templatetags/notices_tags.py
django_one_time_notices-1.0.0.dist-info/METADATA
django_one_time_notices-1.0.0.dist-info/WHEEL
django_one_time_notices-1.0.0.dist-info/RECORD
