Metadata-Version: 2.1
Name: django-one-time-notices
Version: 1.0.0
Summary: 
License: MIT
Author: Becky Smith
Author-email: rebkwok@gmail.com
Requires-Python: >=3.11,<4.0
Classifier: License :: OSI Approved :: MIT License
Classifier: Programming Language :: Python :: 3
Classifier: Programming Language :: Python :: 3.11
Classifier: Programming Language :: Python :: 3.12
Requires-Dist: Django (>=5,<6)
Requires-Dist: django-classy-tags (>=4,<5)
